{
    "AX": {
        "error": 0.00559980753647761,
        "error_type": "SEM",
        "filter_outliers_dict": {
            "filter_outliers": true,
            "iterations": 1,
            "std_devs": 2
        },
        "fit": "average",
        "value": -0.11552832339016182
    },
    "CDD": {
        "error": 2.2486341135184108e-05,
        "error_type": "SEM",
        "filter_outliers_dict": {
            "filter_outliers": true,
            "iterations": 1,
            "std_devs": 10
        },
        "fit": "average",
        "value": 0.00014014084369948023
    },
    "H1": {
        "error": 0.005424431108927845,
        "error_type": "SEM",
        "filter_outliers_dict": {
            "filter_outliers": true,
            "iterations": 1,
            "std_devs": 2
        },
        "fit": "average",
        "value": 0.050056723919045774
    },
    "H2": {
        "error": 0.005965405584250049,
        "error_type": "SEM",
        "filter_outliers_dict": {
            "filter_outliers": true,
            "iterations": 1,
            "std_devs": 2
        },
        "fit": "average",
        "value": -0.027795579018237798
    },
    "L1": {
        "error": 0.005671491298044972,
        "error_type": "SEM",
        "filter_outliers_dict": {
            "filter_outliers": true,
            "iterations": 1,
            "std_devs": 2
        },
        "fit": "average",
        "value": 0.02340505430017455
    },
    "L2": {
        "error": 0.005910155525463564,
        "error_type": "SEM",
        "filter_outliers_dict": {
            "filter_outliers": true,
            "iterations": 1,
            "std_devs": 2
        },
        "fit": "average",
        "value": 0.04220389523044125
    }
}